setup.py
pytest_ipdb.egg-info/PKG-INFO
pytest_ipdb.egg-info/SOURCES.txt
pytest_ipdb.egg-info/dependency_links.txt
pytest_ipdb.egg-info/entry_points.txt
pytest_ipdb.egg-info/requires.txt
pytest_ipdb.egg-info/top_level.txt
pytestipdb/__init__.py
pytestipdb/ptipdb.py