Metadata-Version: 1.1
Name: pytest-ipdb
Version: 0.1-prerelease2
Summary: A py.test plug-in to enable drop to ipdb debugger on test failure.
Home-page: https://github.com/mverteuil/pytest-ipdb
Author: Matthew de Verteuil
Author-email: onceuponajooks@gmail.com
License: UNKNOWN
Platform: UNKNOWN
Classifier: Development Status :: 2 - Pre-Alpha
Classifier: Environment :: Console
Classifier: Environment :: Plugins
Classifier: Intended Audience :: Developers
Classifier: License :: OSI Approved :: MIT License
Classifier: Operating System :: MacOS :: MacOS X
Classifier: Operating System :: POSIX
Classifier: Programming Language :: Python
Classifier: Topic :: Communications :: Email
Classifier: Topic :: Software Development :: Debuggers
Classifier: Topic :: Software Development :: Testing
